tag_parser/__init__.py
tag_parser/basetags.py
tag_parser/decorators.py
tag_parser/models.py
tag_parser/parser.py
tag_parser/tests/__init__.py
tag_parser/tests/test_tags.py
tag_parser/tests/templatetags/__init__.py
tag_parser/tests/templatetags/tag_parser_test_tags.py
django_tag_parser-3.2.dist-info/AUTHORS
django_tag_parser-3.2.dist-info/LICENSE
django_tag_parser-3.2.dist-info/METADATA
django_tag_parser-3.2.dist-info/WHEEL
django_tag_parser-3.2.dist-info/top_level.txt
django_tag_parser-3.2.dist-info/RECORD
